Workbook

Sheet RRHH
A1: Rol | B1: Cantidad | C1: Sueldo Mensual | D1: Costo Mensual
A2: Jefe Proyecto | B2: 1 | C2: 1500000 | D2: =B2*C2 -> 1500000
A3: Arquitecto | B3: 1 | C3: 1500000 | D3: =B3*C3 -> 1500000
A4: Desarrollador Front-End | B4: 1 | C4: 700000 | D4: =B4*C4 -> 700000
A5: Desarrollador Back-End | B5: 1 | C5: 900000 | D5: =B5*C5 -> 900000
A6: QA | B6: 1 | C6: 1000000 | D6: =B6*C6 -> 1000000
A7: Promotor-DevOps | B7: 1 | C7: 1500000 | D7: =B7*C7 -> 1500000
A8: DB | B8: 1 | C8: 900000 | D8: =B8*C8 -> 900000
C11: Total mensual | D11: =SUM(D2:D8) -> 8000000
C12: Total anual | D12: =D11*12 -> 96000000
C13: Total con indirectos (30%) | D13: =D12*1.3 -> 124800000
C14: CAJA | D14: =+D13-D12 -> 28800000

Sheet Licencias
A1: Concepto | B1: Costo Anual
A2: IDEs Desarrollo VsCode | B2: 0
A3: DevOps | B3: 1300000
A4: Cloud (AWS) | B4: 1200000
A5: Testing | B5: 1000000
A6: IDEs POSTGRESQL | B6: 0
A7: IDEs Python | B7: 0
A8: Amazon SES (API correo) | B8: 6750
A9: Total Licencias | B9: =SUM(B2:B8) -> 3506750

Sheet Evaluacion
A1: Concepto | B1: Monto CLP
A2: Costo RRHH Total | B2: =RRHH!D13 -> 124800000
A3: Costo Licencias | B3: =Licencias!B9 -> 3506750
A4: Costo Total Proyecto | B4: =B2+B3 -> 128306750
A5: Beneficio mensual | B5: =+B4/12*1.2 -> 12830675
A6: Beneficio anual | B6: =B5*12 -> 153968100
A7: Ganancia | B7: =B6-B4 -> 25661350
A8: ROI | B8: =(B6-B4)/B4 -> 0.2

Sheet Rendimiento
A1: Concepto | B1: Monto CLP
A2: Costo RRHH Total | B2: =RRHH!D13 -> 124800000
A3: Costo Licencias | B3: =Licencias!B9 -> 3506750
A4: Costo Total Proyecto | B4: =B2+B3 -> 128306750
A5: Beneficio mensual | B5: =+Evaluacion!B5 -> 12830675
A6: Beneficio anual | B6: =B5*12 -> 153968100
A7: Ganancia | B7: =B6-B4 -> 25661350
A8: Rendimiento | B8: =B6/B4 -> 1.2

Sheet EdeCostoyBenefv2
B1: Periodo 0 | C1: Mes1 | D1: Mes2 | E1: Mes3 | F1: Mes4 | G1: Mes5 | H1: Mes6 | I1: Mes7 | J1: Mes8 | K1: Mes9 | L1: Mes10 | M1: Mes11 | N1: Mes12
A2: Beneficio | C2: =+Rendimiento!B5 -> 12830675 | D2: =+C2 -> 12830675 | E2: =+C2 -> 12830675 | F2: =+C2 -> 12830675 | G2: =+C2 -> 12830675 | H2: =+C2 -> 12830675 | I2: =+C2 -> 12830675 | J2: =+C2 -> 12830675 | K2: =+C2 -> 12830675 | L2: =+C2 -> 12830675 | M2: =+C2 -> 12830675 | N2: =+C2 -> 12830675
A3: Costo | C3: =+Rendimiento!B4/12 -> 10692229 | D3: =+C3 -> 10692229 | E3: =+C3 -> 10692229 | F3: =+C3 -> 10692229 | G3: =+C3 -> 10692229 | H3: =+C3 -> 10692229 | I3: =+C3 -> 10692229 | J3: =+C3 -> 10692229 | K3: =+C3 -> 10692229 | L3: =+C3 -> 10692229 | M3: =+C3 -> 10692229 | N3: =+C3 -> 10692229
A4: INVERSION | B4: -3506750 | C4: =C2-C3 -> 2138445.8 | D4: =D2-D3 -> 2138445.8 | E4: =E2-E3 -> 2138445.8 | F4: =F2-F3 -> 2138445.8 | G4: =G2-G3 -> 2138445.8 | H4: =H2-H3 -> 2138445.8 | I4: =I2-I3 -> 2138445.8 | J4: =J2-J3 -> 2138445.8 | ... N4: =N2-N3 -> 2138445.8
A5: Flujos Actualizados | B5: -3506750 | C5: =C4/POWER(1.1,1) -> 1944041.7 | D5: =D4/POWER(1.1,2) -> 1767310.6 | E5: =E4/POWER(1.1,3) -> 1606646 | F5: =F4/POWER(1.1,4) -> 1460587.3 | G5: =G4/POWER(1.1,5) -> 1327806.6 | H5: =H4/POWER(1.1,6) -> 1207096.9 | I5: =I4/POWER(1.1,7) -> 1097360.8 | J5: =J4/POWER(1.1,8) -> 997600.76 | K5: =K4/POWER(1.1,9) -> 906909.78 | L5: =L4/POWER(1.1,10) -> 824463.44 | M5: =M4/POWER(1.1,11) -> 749512.22 | N5: =N4/POWER(1.1,12) -> 681374.74
A7: VAN | B7: {=NPV(0.1,C4:N4)+B4} -> 11063961 | D7: =SUM(B5:N5) -> 11063961
A8: TIR | B8: =IRR(B4:N4) -> 0.60776426 | D8: =IRR(B4:N4) -> 0.60776426
B17: La Inversión para el ejemplo corresponde sólo al periodo 0, del mes1 en adelante corresponde a la diferencia entre el beneficio y el costo
B18: Si el i esta dado por el usuario por ejemplo 10% sino calcular CAPM
